src/__init__.py
src/internal_nodes.py
tests/__init__.py
tests/internal_nodes.py
pynternal_nodes-0.0.2.dist-info/LICENSE
pynternal_nodes-0.0.2.dist-info/METADATA
pynternal_nodes-0.0.2.dist-info/WHEEL
pynternal_nodes-0.0.2.dist-info/top_level.txt
pynternal_nodes-0.0.2.dist-info/RECORD
