Metadata-Version: 2.1
Name: pynternal-nodes
Version: 0.0.2
Summary: A small example with just one function that returns the number of internal nodes on a generic tree composed of consecutive integers
Author-email: Matias Vazquez <mfvazquez@fi.uba.ar>
Project-URL: Homepage, https://github.com/mfvazquez/pynternal_nodes
Project-URL: Bug Tracker, https://github.com/mfvazquez/pynternal_nodes/issues
Classifier: Programming Language :: Python :: 3
Classifier: License :: OSI Approved :: MIT License
Classifier: Operating System :: OS Independent
Requires-Python: >=3.6
License-File: LICENSE
